{"name":"Create an order","id":"reto-aplicativo-swaglab;create-an-order","scenarioId":"reto_aplicativo_SwagLabs:Create an order","methodName":"Create an order","testSteps":[{"number":1,"description":"Given that Diana wants to create an order in the Swag Labs application.","duration":7192,"startTime":"2024-07-09T15:55:09.319190900-05:00[America/Bogota]","screenshots":[{"screenshot":"82770d2a4abb0d6fe6118d04e6944e3c907d7397872283d12db07bde12696801.png","htmlSource":"pagesource14121050689351803524.html","timeStamp":1720558516511,"screenshotName":"82770d2a4abb0d6fe6118d04e6944e3c907d7397872283d12db07bde12696801.png"}],"result":"SUCCESS","precondition":false,"level":0,"children":[{"number":2,"description":"Diana open up","duration":5429,"startTime":"2024-07-09T15:55:09.832874100-05:00[America/Bogota]","screenshots":[{"screenshot":"2b3a9f179e1b1e8574bcfaa992c5105bcd7d25c09c12fc433dad975c3bf345a1.png","htmlSource":"pagesource16651920563922627443.html","timeStamp":1720558515262,"screenshotName":"2b3a9f179e1b1e8574bcfaa992c5105bcd7d25c09c12fc433dad975c3bf345a1.png"}],"result":"SUCCESS","precondition":false,"level":1,"children":[{"number":3,"description":"Diana opens the Swag labs page","duration":5280,"startTime":"2024-07-09T15:55:09.856660100-05:00[America/Bogota]","screenshots":[{"screenshot":"2b3a9f179e1b1e8574bcfaa992c5105bcd7d25c09c12fc433dad975c3bf345a1.png","htmlSource":"pagesource10444627764862239458.html","timeStamp":1720558515136,"screenshotName":"2b3a9f179e1b1e8574bcfaa992c5105bcd7d25c09c12fc433dad975c3bf345a1.png"}],"result":"SUCCESS","precondition":false,"level":2}]},{"number":4,"description":"Diana login","duration":1100,"startTime":"2024-07-09T15:55:15.264959600-05:00[America/Bogota]","screenshots":[{"screenshot":"82770d2a4abb0d6fe6118d04e6944e3c907d7397872283d12db07bde12696801.png","htmlSource":"pagesource8608646987643805127.html","timeStamp":1720558516365,"screenshotName":"82770d2a4abb0d6fe6118d04e6944e3c907d7397872283d12db07bde12696801.png"}],"result":"SUCCESS","precondition":false,"level":1,"children":[{"number":5,"description":"Diana enters \u0027standard_user\u0027 into ","duration":385,"startTime":"2024-07-09T15:55:15.315821300-05:00[America/Bogota]","screenshots":[{"screenshot":"afb44d2c57103553d19eabeeb5c2d03fd6bd3847176a2c590451f807c56e4856.png","htmlSource":"pagesource3089173058841399162.html","timeStamp":1720558515700,"screenshotName":"afb44d2c57103553d19eabeeb5c2d03fd6bd3847176a2c590451f807c56e4856.png"}],"result":"SUCCESS","precondition":false,"level":2},{"number":6,"description":"Diana enters \u0027secret_sauce\u0027 into ","duration":240,"startTime":"2024-07-09T15:55:15.702023800-05:00[America/Bogota]","screenshots":[{"screenshot":"71550eda853fb52a93e53c3cd9dc6f28a8f4bde72c06449830de4d0b156dc91e.png","htmlSource":"pagesource227413046478227660.html","timeStamp":1720558515941,"screenshotName":"71550eda853fb52a93e53c3cd9dc6f28a8f4bde72c06449830de4d0b156dc91e.png"}],"result":"SUCCESS","precondition":false,"level":2},{"number":7,"description":"Diana clicks on ","duration":347,"startTime":"2024-07-09T15:55:15.943215800-05:00[America/Bogota]","screenshots":[{"screenshot":"82770d2a4abb0d6fe6118d04e6944e3c907d7397872283d12db07bde12696801.png","htmlSource":"pagesource15875317975641754079.html","timeStamp":1720558516290,"screenshotName":"82770d2a4abb0d6fe6118d04e6944e3c907d7397872283d12db07bde12696801.png"}],"result":"SUCCESS","precondition":false,"level":2}]}]},{"number":8,"description":"When she adds products to the cart in the Swag Labs application.","duration":1540,"startTime":"2024-07-09T15:55:16.513022900-05:00[America/Bogota]","screenshots":[{"screenshot":"7cbee2a49a53c8f7475e42c0a56cc89ef7f8f0dc7a2ae8d3050b5e88ba10a267.png","htmlSource":"pagesource12342945768618089739.html","timeStamp":1720558518053,"screenshotName":"7cbee2a49a53c8f7475e42c0a56cc89ef7f8f0dc7a2ae8d3050b5e88ba10a267.png"}],"result":"SUCCESS","precondition":false,"level":0,"children":[{"number":9,"description":"Diana select products","duration":1356,"startTime":"2024-07-09T15:55:16.527116200-05:00[America/Bogota]","screenshots":[{"screenshot":"7cbee2a49a53c8f7475e42c0a56cc89ef7f8f0dc7a2ae8d3050b5e88ba10a267.png","htmlSource":"pagesource7595782570826506852.html","timeStamp":1720558517884,"screenshotName":"7cbee2a49a53c8f7475e42c0a56cc89ef7f8f0dc7a2ae8d3050b5e88ba10a267.png"}],"result":"SUCCESS","precondition":false,"level":1,"children":[{"number":10,"description":"Diana clicks on ","duration":407,"startTime":"2024-07-09T15:55:16.539226800-05:00[America/Bogota]","screenshots":[{"screenshot":"8517dac5d9541bd4ea3ae089fdaaa1eb54e2067c63bb35b293e72419b1167a03.png","htmlSource":"pagesource15404710610743154531.html","timeStamp":1720558516947,"screenshotName":"8517dac5d9541bd4ea3ae089fdaaa1eb54e2067c63bb35b293e72419b1167a03.png"}],"result":"SUCCESS","precondition":false,"level":2},{"number":11,"description":"Diana clicks on ","duration":335,"startTime":"2024-07-09T15:55:16.949833-05:00[America/Bogota]","screenshots":[{"screenshot":"77820701323a392a44c07136897bd3e13fe521cb36f74e31236b77db3234e7e2.png","htmlSource":"pagesource2802556864736715008.html","timeStamp":1720558517284,"screenshotName":"77820701323a392a44c07136897bd3e13fe521cb36f74e31236b77db3234e7e2.png"}],"result":"SUCCESS","precondition":false,"level":2},{"number":12,"description":"Diana clicks on ","duration":406,"startTime":"2024-07-09T15:55:17.287020100-05:00[America/Bogota]","screenshots":[{"screenshot":"7cbee2a49a53c8f7475e42c0a56cc89ef7f8f0dc7a2ae8d3050b5e88ba10a267.png","htmlSource":"pagesource15528599951671299773.html","timeStamp":1720558517693,"screenshotName":"7cbee2a49a53c8f7475e42c0a56cc89ef7f8f0dc7a2ae8d3050b5e88ba10a267.png"}],"result":"SUCCESS","precondition":false,"level":2}]}]},{"number":13,"description":"Then she can complete the order to checkout.","duration":2815,"startTime":"2024-07-09T15:55:18.055591900-05:00[America/Bogota]","screenshots":[{"screenshot":"ec7970aff5d354adbe9e14cd7445c540d079862fa4c50f1c6e8a7ff1179ab2fb.png","htmlSource":"pagesource16536799172725174376.html","timeStamp":1720558520870,"screenshotName":"ec7970aff5d354adbe9e14cd7445c540d079862fa4c50f1c6e8a7ff1179ab2fb.png"}],"result":"SUCCESS","precondition":false,"level":0,"children":[{"number":14,"description":"Diana do checkout","duration":2607,"startTime":"2024-07-09T15:55:18.076335100-05:00[America/Bogota]","screenshots":[{"screenshot":"ec7970aff5d354adbe9e14cd7445c540d079862fa4c50f1c6e8a7ff1179ab2fb.png","htmlSource":"pagesource2215627495897559231.html","timeStamp":1720558520684,"screenshotName":"ec7970aff5d354adbe9e14cd7445c540d079862fa4c50f1c6e8a7ff1179ab2fb.png"}],"result":"SUCCESS","precondition":false,"level":1,"children":[{"number":15,"description":"Diana clicks on ","duration":374,"startTime":"2024-07-09T15:55:18.105033700-05:00[America/Bogota]","screenshots":[{"screenshot":"181dfc459e68c636de954cb5f5d95c258846cfee7c399f282db393aef11504a7.png","htmlSource":"pagesource13199973323095465122.html","timeStamp":1720558518479,"screenshotName":"181dfc459e68c636de954cb5f5d95c258846cfee7c399f282db393aef11504a7.png"}],"result":"SUCCESS","precondition":false,"level":2},{"number":16,"description":"Diana enters \u0027Diana\u0027 into ","duration":302,"startTime":"2024-07-09T15:55:18.481442900-05:00[America/Bogota]","screenshots":[{"screenshot":"70ba49850428cdc3eaef61b7e212147d5db1c4fd4d1dda1adc9ccbc6747849fc.png","htmlSource":"pagesource240508890783664047.html","timeStamp":1720558518783,"screenshotName":"70ba49850428cdc3eaef61b7e212147d5db1c4fd4d1dda1adc9ccbc6747849fc.png"}],"result":"SUCCESS","precondition":false,"level":2},{"number":17,"description":"Diana enters \u0027G\u0027 into ","duration":371,"startTime":"2024-07-09T15:55:18.785636900-05:00[America/Bogota]","screenshots":[{"screenshot":"a54c722b87f593bd9f844e23a75d0ea6997112eefa48021764fcc0f580ddfd9b.png","htmlSource":"pagesource17601588590993955791.html","timeStamp":1720558519155,"screenshotName":"a54c722b87f593bd9f844e23a75d0ea6997112eefa48021764fcc0f580ddfd9b.png"}],"result":"SUCCESS","precondition":false,"level":2},{"number":18,"description":"Diana enters \u0027100052\u0027 into ","duration":341,"startTime":"2024-07-09T15:55:19.159210500-05:00[America/Bogota]","screenshots":[{"screenshot":"d21956977f5147a9a4f89011a0b6acbd26cd0d10313a23291fd1691591126e7d.png","htmlSource":"pagesource7409724394003126602.html","timeStamp":1720558519500,"screenshotName":"d21956977f5147a9a4f89011a0b6acbd26cd0d10313a23291fd1691591126e7d.png"}],"result":"SUCCESS","precondition":false,"level":2},{"number":19,"description":"Diana clicks on ","duration":565,"startTime":"2024-07-09T15:55:19.501577300-05:00[America/Bogota]","screenshots":[{"screenshot":"7b2ca3f434a666a19208f2e8aa53f319f608ad027fef7d67e7e1c8a41e115329.png","htmlSource":"pagesource7391674375620235317.html","timeStamp":1720558520067,"screenshotName":"7b2ca3f434a666a19208f2e8aa53f319f608ad027fef7d67e7e1c8a41e115329.png"}],"result":"SUCCESS","precondition":false,"level":2},{"number":20,"description":"Diana clicks on ","duration":465,"startTime":"2024-07-09T15:55:20.070193800-05:00[America/Bogota]","screenshots":[{"screenshot":"ec7970aff5d354adbe9e14cd7445c540d079862fa4c50f1c6e8a7ff1179ab2fb.png","htmlSource":"pagesource4250249053220771938.html","timeStamp":1720558520535,"screenshotName":"ec7970aff5d354adbe9e14cd7445c540d079862fa4c50f1c6e8a7ff1179ab2fb.png"}],"result":"SUCCESS","precondition":false,"level":2}]}]}],"userStory":{"id":"reto_aplicativo_SwagLabs","storyName":"Reto_aplicativo_SwagLab","displayName":"Reto_aplicativo_SwagLab","path":"reto_aplicativo_SwagLabs","pathElements":[{"name":"reto_aplicativo_SwagLabs","description":""}],"narrative":"  As a user, I want to create an order in the Swag Labs application.","type":"feature"},"title":"Create an order","description":"","tags":[{"name":"Chrome","type":"context","displayName":"Chrome"},{"name":"Windows","type":"context","displayName":"Windows"},{"name":"Stories","type":"tag","displayName":"Stories"},{"name":"Chrome, Windows","type":"context","displayName":"Chrome, Windows"},{"name":"happypathTest","type":"tag","displayName":"happypathTest"}],"startTime":"2024-07-09T15:55:09.232773800-05:00[America/Bogota]","duration":5578,"projectKey":"","sessionId":"2772d29c223cec07d5128e940b5d263b","driver":"chrome:diana","isManualTestingUpToDate":false,"context":"chrome,windows","manual":false,"testSource":"Cucumber","actors":[{"name":"Diana","can":["browse the web"]}],"order":0,"result":"SUCCESS"}